README.md
setup.cfg
setup.py
cloudmersive_security_api_client/__init__.py
cloudmersive_security_api_client/api_client.py
cloudmersive_security_api_client/configuration.py
cloudmersive_security_api_client/rest.py
cloudmersive_security_api_client.egg-info/PKG-INFO
cloudmersive_security_api_client.egg-info/SOURCES.txt
cloudmersive_security_api_client.egg-info/dependency_links.txt
cloudmersive_security_api_client.egg-info/requires.txt
cloudmersive_security_api_client.egg-info/top_level.txt
cloudmersive_security_api_client/api/__init__.py
cloudmersive_security_api_client/api/content_threat_detection_api.py
cloudmersive_security_api_client/api/network_threat_detection_api.py
cloudmersive_security_api_client/models/__init__.py
cloudmersive_security_api_client/models/ip_threat_detection_response.py
cloudmersive_security_api_client/models/string_automatic_threat_detection.py
cloudmersive_security_api_client/models/string_insecure_deserialization_json_detection.py
cloudmersive_security_api_client/models/string_sql_injection_detection_result.py
cloudmersive_security_api_client/models/string_xss_protection_result.py
cloudmersive_security_api_client/models/string_xxe_detection_result.py
cloudmersive_security_api_client/models/threat_detection_bot_check_response.py
cloudmersive_security_api_client/models/threat_detection_tor_node_response.py
cloudmersive_security_api_client/models/url_ssrf_threat_detection_request_full.py
cloudmersive_security_api_client/models/url_ssrf_threat_detection_response_full.py
test/__init__.py
test/test_content_threat_detection_api.py
test/test_ip_threat_detection_response.py
test/test_network_threat_detection_api.py
test/test_string_automatic_threat_detection.py
test/test_string_insecure_deserialization_json_detection.py
test/test_string_sql_injection_detection_result.py
test/test_string_xss_protection_result.py
test/test_string_xxe_detection_result.py
test/test_threat_detection_bot_check_response.py
test/test_threat_detection_tor_node_response.py
test/test_url_ssrf_threat_detection_request_full.py
test/test_url_ssrf_threat_detection_response_full.py