Metadata-Version: 2.1
Name: cloudmersive-security-api-client
Version: 3.0.1
Summary: securityapi
Home-page: https://www.cloudmersive.com/security-threat-detection-api
Author-email: 
License: UNKNOWN
Keywords: Swagger,securityapi
Platform: UNKNOWN
